{
  "lumiose-city": {
    "gift": [
      1,
      4,
      7
    ]
  },
  "kalos-route-2": {
    "wild": [
      10,
      13,
      16,
      263,
      659,
      661,
      664
    ]
  },
  "santalune-forest": {
    "wild": [
      10,
      11,
      13,
      14,
      25,
      511,
      513,
      515,
      661,
      664
    ]
  },
  "kalos-route-3": {
    "wild": [
      16,
      25,
      206,
      298,
      399,
      412,
      659,
      661
    ],
    "fishing": [
      118,
      119,
      129,
      130,
      341,
      342
    ],
    "surfing": [
      183,
      284
    ]
  },
  "kalos-route-14": {
    "wild": [
      23,
      69,
      70,
      93,
      195,
      451,
      455,
      588,
      616,
      618,
      704
    ],
    "fishing": [
      60,
      61,
      339,
      340
    ],
    "surfing": [
      195,
      618,
      704
    ]
  },
  "kalos-route-19": {
    "wild": [
      24,
      70,
      93,
      195,
      207,
      452,
      455,
      588,
      616,
      618,
      705
    ],
    "fishing": [
      60,
      61,
      186,
      339,
      340
    ],
    "surfing": [
      195,
      618,
      705
    ]
  },
  "kalos-route-18": {
    "wild": [
      28,
      74,
      75,
      213,
      247,
      305,
      324,
      533,
      631,
      632
    ]
  },
  "terminus-cave-1f": {
    "wild": [
      28,
      74,
      75,
      213,
      246,
      247,
      304,
      305,
      632
    ]
  },
  "terminus-cave-b1f-left": {
    "wild": [
      28,
      74,
      75,
      213,
      246,
      247,
      304,
      305,
      632
    ]
  },
  "terminus-cave-b1f-right": {
    "wild": [
      28,
      74,
      75,
      213,
      246,
      247,
      304,
      305,
      632
    ]
  },
  "terminus-cave-b2f": {
    "wild": [
      28,
      74,
      75,
      246,
      247,
      304,
      305,
      632
    ]
  },
  "terminus-cave-zygardes-chamber": {
    "wild": [
      28,
      74,
      75,
      246,
      247,
      304,
      305,
      632
    ],
    "static": [
      718
    ]
  },
  "kalos-route-11": {
    "wild": [
      29,
      30,
      32,
      33,
      297,
      396,
      397,
      433,
      434,
      538,
      539,
      702
    ]
  },
  "kalos-route-20": {
    "wild": [
      39,
      164,
      185,
      571,
      575,
      590,
      591,
      709
    ]
  },
  "pokemon-village": {
    "wild": [
      39,
      60,
      132,
      164,
      271,
      571,
      575,
      590,
      591
    ],
    "fishing": [
      60,
      61,
      550
    ],
    "surfing": [
      61,
      271
    ]
  },
  "connecting-cave": {
    "wild": [
      41,
      293,
      307,
      610
    ]
  },
  "kalos-route-6": {
    "wild": [
      43,
      161,
      290,
      352,
      677,
      679
    ]
  },
  "kalos-route-13": {
    "wild": [
      51,
      75,
      218,
      328,
      443
    ]
  },
  "kalos-route-7": {
    "wild": [
      54,
      187,
      235,
      313,
      314,
      315,
      453,
      580,
      669,
      682,
      684
    ],
    "static": [
      143
    ]
  },
  "kalos-route-22": {
    "wild": [
      54,
      83,
      184,
      206,
      298,
      399,
      400,
      447,
      659,
      660,
      667
    ],
    "surfing": [
      54,
      184
    ],
    "fishing": [
      118,
      119,
      129,
      130,
      318,
      319
    ]
  },
  "couriway-town": {
    "fishing": [
      60,
      61,
      550
    ],
    "surfing": [
      271,
      419
    ]
  },
  "laverre-city": {
    "fishing": [
      60,
      61,
      550
    ]
  },
  "kalos-route-15": {
    "fishing": [
      60,
      61,
      550
    ],
    "wild": [
      198,
      262,
      451,
      505,
      510,
      590,
      624,
      707
    ],
    "surfing": [
      271,
      419
    ]
  },
  "kalos-route-16": {
    "fishing": [
      60,
      61,
      550
    ],
    "wild": [
      70,
      198,
      419,
      451,
      590,
      707,
      708,
      710
    ],
    "surfing": [
      271,
      419
    ]
  },
  "kalos-route-21": {
    "fishing": [
      60,
      61,
      147,
      148,
      550
    ],
    "wild": [
      123,
      217,
      327,
      333,
      334,
      419
    ],
    "surfing": [
      271,
      419
    ]
  },
  "frost-cavern-unknown-area-313": {
    "fishing": [
      60,
      61,
      550
    ],
    "surfing": [
      61,
      419
    ],
    "wild": [
      238,
      582,
      613
    ]
  },
  "frost-cavern-unknown-area-315": {
    "fishing": [
      60,
      61,
      550
    ],
    "surfing": [
      61,
      419
    ],
    "wild": [
      93,
      124,
      221,
      238,
      582,
      613,
      614,
      615,
      712
    ]
  },
  "kalos-victory-road-unknown-area-322": {
    "fishing": [
      60,
      61,
      550
    ],
    "surfing": [
      61,
      419
    ],
    "wild": [
      74,
      75,
      93,
      108,
      213,
      419,
      533,
      621,
      634
    ]
  },
  "kalos-victory-road-outside": {
    "fishing": [
      60,
      61,
      550
    ],
    "surfing": [
      271,
      419
    ]
  },
  "kalos-victory-road-unknown-area-328": {
    "fishing": [
      60,
      61,
      62,
      550
    ],
    "surfing": [
      61,
      419
    ],
    "wild": [
      74,
      75,
      93,
      108,
      419,
      533,
      621,
      634
    ]
  },
  "kalos-route-5": {
    "wild": [
      63,
      84,
      311,
      312,
      316,
      559,
      659,
      672,
      674,
      676
    ]
  },
  "glittering-cave-unknown-area-303": {
    "wild": [
      66,
      95,
      104,
      111,
      115,
      303,
      337,
      338
    ],
    "gift": [
      696,
      698
    ]
  },
  "ambrette-town": {
    "surfing": [
      72,
      320
    ],
    "fishing": [
      116,
      117,
      369,
      370,
      690,
      691,
      692,
      693
    ],
    "wild": [
      557,
      688
    ]
  },
  "cyllage-city": {
    "surfing": [
      72,
      320
    ],
    "wild": [
      95,
      557,
      688
    ],
    "fishing": [
      116,
      117,
      369,
      370,
      690,
      691,
      692,
      693
    ]
  },
  "shalour-city": {
    "surfing": [
      72,
      458
    ],
    "fishing": [
      170,
      171,
      223,
      224,
      370,
      594
    ]
  },
  "kalos-route-8": {
    "surfing": [
      72,
      320
    ],
    "fishing": [
      90,
      91,
      120,
      121,
      211,
      370,
      690,
      691,
      692,
      693
    ],
    "wild": [
      276,
      278,
      325,
      335,
      336,
      359,
      371,
      425,
      557,
      619,
      686,
      688
    ]
  },
  "kalos-route-12": {
    "surfing": [
      72,
      131,
      458
    ],
    "wild": [
      79,
      102,
      127,
      128,
      179,
      214,
      241,
      278,
      417,
      441,
      557,
      688
    ],
    "gift": [
      131
    ],
    "fishing": [
      222,
      223,
      224,
      366,
      367,
      368,
      370
    ]
  },
  "azure-bay": {
    "surfing": [
      72,
      131,
      458
    ],
    "wild": [
      79,
      102,
      278,
      441,
      557,
      686,
      688
    ],
    "fishing": [
      170,
      171,
      223,
      224,
      370,
      594
    ]
  },
  "kalos-victory-road-unknown-area-324": {
    "wild": [
      74,
      75,
      93,
      108,
      213,
      533,
      621,
      634
    ]
  },
  "kalos-victory-road-unknown-area-326": {
    "wild": [
      74,
      75,
      93,
      108,
      533,
      621,
      634
    ]
  },
  "lost-hotel": {
    "wild": [
      82,
      101,
      607,
      624,
      707
    ]
  },
  "frost-cavern-unknown-area-314": {
    "wild": [
      93,
      124,
      221,
      238,
      582,
      613,
      614,
      615,
      712
    ]
  },
  "frost-cavern-unknown-area-316": {
    "wild": [
      93,
      124,
      221,
      238,
      582,
      613,
      614,
      615,
      712
    ]
  },
  "frost-cavern-unknown-area-317": {
    "wild": [
      93,
      124,
      221,
      238,
      582,
      613,
      614,
      615,
      712
    ]
  },
  "glittering-cave-unknown-area-304": {
    "wild": [
      95,
      557
    ]
  },
  "parfum-palace": {
    "fishing": [
      118,
      119,
      129,
      130,
      341,
      342
    ]
  },
  "reflection-cave-unknown-area-305": {
    "wild": [
      122,
      202,
      302,
      433,
      439,
      524,
      577,
      703
    ]
  },
  "reflection-cave-unknown-area-306": {
    "wild": [
      122,
      202,
      302,
      433,
      439,
      524,
      577,
      703
    ]
  },
  "reflection-cave-unknown-area-307": {
    "wild": [
      122,
      202,
      302,
      433,
      439,
      524,
      577,
      703
    ]
  },
  "reflection-cave-unknown-area-308": {
    "wild": [
      122,
      202,
      302,
      433,
      439,
      524,
      577,
      703
    ]
  },
  "kalos-route-10": {
    "wild": [
      133,
      193,
      209,
      228,
      299,
      309,
      561,
      587,
      622,
      701
    ]
  },
  "sea-spirits-den": {
    "static": [
      144,
      145,
      146
    ]
  },
  "roaming-kalos": {
    "static": [
      144,
      145,
      146
    ]
  },
  "unknown-dungeon": {
    "static": [
      150
    ]
  },
  "kalos-route-4": {
    "wild": [
      165,
      280,
      300,
      406,
      415,
      669
    ]
  },
  "kalos-route-17": {
    "wild": [
      215,
      225,
      459,
      460
    ]
  },
  "tower-of-mastery": {
    "gift": [
      448
    ]
  },
  "kalos-route-9": {
    "wild": [
      449,
      551,
      694
    ]
  },
  "aquacorde-town": {
    "gift": [
      650,
      653,
      656
    ]
  },
  "team-flare-secret-hq": {
    "static": [
      716,
      717
    ]
  }
}